tokenscope/__init__.py
tokenscope/core.py
tokenscope/server.py
tokenscope-0.2.0.dist-info/licenses/LICENSE
tokenscope-0.2.0.dist-info/METADATA
tokenscope-0.2.0.dist-info/WHEEL
tokenscope-0.2.0.dist-info/entry_points.txt
tokenscope-0.2.0.dist-info/top_level.txt
tokenscope-0.2.0.dist-info/RECORD
