Metadata-Version: 2.4
Name: tokenscope
Version: 0.2.0
Summary: TokenScope: Token-Aware Directory Explorer for LLMs
Author-email: Carlos Gaete <cdgaete@gmail.com>
License: MIT
Project-URL: Homepage, https://github.com/cdgaete/token-scope-mcp
Project-URL: Bug Tracker, https://github.com/cdgaete/token-scope-mcp/issues
Project-URL: Source Code, https://github.com/cdgaete/token-scope-mcp
Keywords: mcp,directory,explorer,claude,ai,assistant,token-aware
Classifier: Development Status :: 4 - Beta
Classifier: Intended Audience :: Developers
Classifier: License :: OSI Approved :: MIT License
Classifier: Programming Language :: Python :: 3
Classifier: Programming Language :: Python :: 3.10
Classifier: Programming Language :: Python :: 3.11
Classifier: Programming Language :: Python :: 3.12
Classifier: Programming Language :: Python :: 3.13
Classifier: Topic :: Software Development :: Libraries :: Python Modules
Classifier: Topic :: Utilities
Requires-Python: >=3.10
License-File: LICENSE
Requires-Dist: fastmcp>=1.0.0
Requires-Dist: tiktoken>=0.9.0
Provides-Extra: dev
Requires-Dist: pytest>=8.3.5; extra == "dev"
Requires-Dist: black>=24.3.0; extra == "dev"
Requires-Dist: ruff>=0.3.4; extra == "dev"
Requires-Dist: build>=1.2.1; extra == "dev"
Dynamic: license-file
